redash_python_modification/__init__.py
redash_python_modification/redash.py
redash_python_modification/services/__init__.py
redash_python_modification/services/alerts.py
redash_python_modification/services/base.py
redash_python_modification/services/dashboards.py
redash_python_modification/services/data_sources.py
redash_python_modification/services/destinations.py
redash_python_modification/services/groups.py
redash_python_modification/services/mixins.py
redash_python_modification/services/queries.py
redash_python_modification/services/query_snippets.py
redash_python_modification/services/users.py
redash_python_modification/services/widgets.py
redash_python_modification-0.0.3.dist-info/LICENSE
redash_python_modification-0.0.3.dist-info/METADATA
redash_python_modification-0.0.3.dist-info/WHEEL
redash_python_modification-0.0.3.dist-info/top_level.txt
redash_python_modification-0.0.3.dist-info/RECORD
