Metadata-Version: 2.1
Name: redash-python-modification
Version: 0.0.3
Summary: Modification in fetch page to be able to get all queries instead of 25
Author-email: karenarcoverde <arcoverdek@gmail.com>
License: BSD-2-Clause
Project-URL: Homepage, https://github.com/karenarcoverde/redash-python
Project-URL: Documentation, https://blacksuan19.dev/redash-python
Project-URL: Repository, https://github.com/blacksuan19/redash-python/
Project-URL: Issues, https://github.com/blacksuan19/redash-python/issues
Keywords: redash
Classifier: License :: OSI Approved :: BSD License
Classifier: Programming Language :: Python
Classifier: Programming Language :: Python :: 3
Requires-Python: >=3.7
License-File: LICENSE
Requires-Dist: requests
Provides-Extra: dev
Requires-Dist: black ; extra == 'dev'
Requires-Dist: bumpver ; extra == 'dev'
Requires-Dist: pip-tools ; extra == 'dev'
Requires-Dist: wheel ; extra == 'dev'
Requires-Dist: requests ; extra == 'dev'
